eventemitter/__init__.py
gevent_eventemitter-2.1.dist-info/DESCRIPTION.rst
gevent_eventemitter-2.1.dist-info/METADATA
gevent_eventemitter-2.1.dist-info/RECORD
gevent_eventemitter-2.1.dist-info/WHEEL
gevent_eventemitter-2.1.dist-info/metadata.json
gevent_eventemitter-2.1.dist-info/top_level.txt
gevent_eventemitter-2.1.dist-info/zip-safe
