Metadata-Version: 1.1
Name: gevent-eventemitter
Version: 2.1
Summary: Implements EventEmitter using gevent
Home-page: https://github.com/rossengeorgiev/gevent-eventemitter
Author: Rossen Georgiev
Author-email: rossen@rgp.io
License: MIT
Keywords: gevent event emitter ee greenlet
Platform: UNKNOWN
Classifier: Development Status :: 5 - Production/Stable
Classifier: Intended Audience :: Developers
Classifier: License :: OSI Approved :: MIT License
Classifier: Topic :: Software Development :: Libraries :: Python Modules
Classifier: Natural Language :: English
Classifier: Operating System :: OS Independent
